lemenv/__init__.py
lemenv/cli.py
lemenv/manager.py
lemenv/utils.py
lemenv-0.1.2.dist-info/METADATA
lemenv-0.1.2.dist-info/WHEEL
lemenv-0.1.2.dist-info/entry_points.txt
lemenv-0.1.2.dist-info/licenses/LICENSE
lemenv-0.1.2.dist-info/RECORD
