Metadata-Version: 2.3
Name: lemenv
Version: 0.1.2
Summary: A Citrus-Flavored Virtual Environment Manager
Project-URL: Homepage, https://github.com/jakerains/lemenv
Project-URL: Repository, https://github.com/jakerains/lemenv.git
Project-URL: Issues, https://github.com/jakerains/lemenv/issues
Author-email: Jake Rains <your.email@example.com>
License: MIT License
Keywords: conda,environment manager,venv,virtual environment
Classifier: Development Status :: 3 - Alpha
Classifier: Intended Audience :: Developers
Classifier: License :: OSI Approved :: MIT License
Classifier: Programming Language :: Python :: 3
Classifier: Programming Language :: Python :: 3.6
Classifier: Programming Language :: Python :: 3.7
Classifier: Programming Language :: Python :: 3.8
Classifier: Programming Language :: Python :: 3.9
Classifier: Programming Language :: Python :: 3.10
Classifier: Programming Language :: Python :: 3.11
Classifier: Topic :: Software Development :: Build Tools
Requires-Python: >=3.6
Requires-Dist: click
Requires-Dist: colorama
Requires-Dist: inquirer
Provides-Extra: dev
Requires-Dist: black; extra == 'dev'
Requires-Dist: build; extra == 'dev'
Requires-Dist: isort; extra == 'dev'
Requires-Dist: pytest; extra == 'dev'
Requires-Dist: twine; extra == 'dev'
